_archive.so
_context.so
_data.so
_exclusive_publication.so
_publication.so
_subscription.so
aeronpy/__init__.py
aeronpy/archive.py
aeronpy/archive.pyi
aeronpy/context.py
aeronpy/context.pyi
aeronpy/data.py
aeronpy/data.pyi
aeronpy/exclusive_publication.py
aeronpy/exclusive_publication.pyi
aeronpy/publication.py
aeronpy/publication.pyi
aeronpy/subscription.py
aeronpy/subscription.pyi
aeron_python-1.0.0.dist-info/LICENSE
aeron_python-1.0.0.dist-info/METADATA
aeron_python-1.0.0.dist-info/WHEEL
aeron_python-1.0.0.dist-info/top_level.txt
aeron_python-1.0.0.dist-info/RECORD
