Metadata-Version: 2.1
Name: aeron-python
Version: 1.0.0
Summary: Python bindings for Aeron
Home-page: https://github.com/fairtide/aeron-python
Author: Fairtide Pte
Author-email: UNKNOWN
License: Apache 2.0
Platform: UNKNOWN
Requires-Python: >=3.6.*
